MANIFEST.in
README.md
setup.py
django_makeconf.egg-info/PKG-INFO
django_makeconf.egg-info/SOURCES.txt
django_makeconf.egg-info/dependency_links.txt
django_makeconf.egg-info/top_level.txt
makeconf/__init__.py
makeconf/management/__init__.py
makeconf/management/commands/__init__.py
makeconf/management/commands/makeconf.py
makeconf/templatetags/__init__.py
makeconf/templatetags/makeconf.py