Metadata-Version: 1.1
Name: django-makeconf
Version: 1.1.0
Summary: A Django app that provides commands to build deployment and other configuration files based on Django settings.
Home-page: https://github.com/ethanmcc/django-makeconf
Author: Ethan McCreadie
Author-email: ethanmcc@gmail.com
License: BSD License
Platform: UNKNOWN
Classifier: Environment :: Web Environment
Classifier: Framework :: Django
Classifier: Intended Audience :: Developers
Classifier: License :: OSI Approved :: BSD License
Classifier: Operating System :: OS Independent
Classifier: Programming Language :: Python
Classifier: Programming Language :: Python :: 3
Classifier: Programming Language :: Python :: 3.2
Classifier: Programming Language :: Python :: 3.3
Classifier: Topic :: Internet :: WWW/HTTP
Classifier: Topic :: Internet :: WWW/HTTP :: Dynamic Content
